eralegis/__init__.py
eralegis/thelemicdate.py
eralegis-0.1.4.dist-info/LICENSE
eralegis-0.1.4.dist-info/METADATA
eralegis-0.1.4.dist-info/WHEEL
eralegis-0.1.4.dist-info/top_level.txt
eralegis-0.1.4.dist-info/RECORD
