Metadata-Version: 2.1
Name: eralegis
Version: 0.1.4
Summary: Projeto simples para calculo de data thelemica
Home-page: https://github.com/tiagocordeiro/eralegis
Author: Tiago Cordeiro
Author-email: tiago@mulhergorila.com
License: MIT
Classifier: Development Status :: 4 - Beta
Classifier: Environment :: Web Environment
Classifier: Intended Audience :: Developers
Classifier: License :: OSI Approved :: MIT License
Classifier: Operating System :: OS Independent
Classifier: Programming Language :: Python
Classifier: Programming Language :: Python :: 3
Classifier: Framework :: Paste
License-File: LICENSE
Requires-Dist: flatlib >=0.2.3
